Workbook

Sheet Main (All in One)
A1: Business Tax Planner - Main (All in One)
A3: Assumptions & Inputs
A4: Financial Year Start | B4: 01-APR-2026
A5: Financial Year End | B5: 31-MAR-2027
A6: Currency | B6: INR
A7: Tax Model | B7: Corporate Tax
A8: GST/VAT Included? | B8: Yes
A9: Base Tax Rate | B9: 0.25
A10: Surcharge Rate | B10: 0
A11: Cess Rate | B11: 0.04
A12: Eligible Deductions | B12: 0
A13: Advance Tax Paid (YTD) | B13: 0
A14: Planned Tax Payment Now | B14: 0
A15: KPI Summary
A16: YTD Sales | B16: =SUM('Current Year Data'!B2:B13)
A17: YTD Purchase | B17: =SUM('Current Year Data'!C2:C13)
A18: YTD Profit/Loss | B18: =SUM('Current Year Data'!E2:E13)
A19: Predicted Year-End Sales | B19: ='All Predictions'!M2
A20: Predicted Year-End Purchase | B20: ='All Predictions'!M3
A21: Predicted Year-End Profit | B21: ='All Predictions'!M4
A22: Predicted Tax Payable | B22: ='All Predictions'!M6
A23: Tax Already Paid | B23: =B13
A24: Balance Tax to Pay | B24: =MAX(B23-B24,0)
A25: Remaining After Planned Payment | B25: =MAX(B25-B14,0)
A26: Months Remaining | B26: =COUNTIF('Current Year Data'!G2:G13,"Pending")
A27: Suggested Monthly Payment | B27: =IF(B27>0,B26/B27,0)
A28: Cash Buffer Recommendation (10%) | B28: =B26*0.10
A31: Alert Flags
A32: Underpaid risk | B32: =IF(B25>0,"Yes","No")
A33: Overpayment likely | B33: =IF(B14>B23,"Yes","No")
A34: Profit drop warning | B34: =IF(B22<B18,"Yes","No")

Sheet Last Year Data
A1: Month | B1: Sales | C1: Purchase | D1: Other Expenses | E1: Profit/Loss | F1: Tax Paid
A2: Apr | E2: =B2-C2-D2
A3: May | E3: =B3-C3-D3
A4: Jun | E4: =B4-C4-D4
A5: Jul | E5: =B5-C5-D5
A6: Aug | E6: =B6-C6-D6
A7: Sep | E7: =B7-C7-D7
A8: Oct | E8: =B8-C8-D8
A9: Nov | E9: =B9-C9-D9
A10: Dec | E10: =B10-C10-D10
A11: Jan | E11: =B11-C11-D11
A12: Feb | E12: =B12-C12-D12
A13: Mar | E13: =B13-C13-D13

Sheet Current Year Data
A1: Month | B1: Sales | C1: Purchase | D1: Other Expenses | E1: Profit/Loss | F1: Tax Paid | G1: Status
A2: Apr | E2: =B2-C2-D2 | G2: Pending
A3: May | E3: =B3-C3-D3 | G3: Pending
A4: Jun | E4: =B4-C4-D4 | G4: Pending
A5: Jul | E5: =B5-C5-D5 | G5: Pending
A6: Aug | E6: =B6-C6-D6 | G6: Pending
A7: Sep | E7: =B7-C7-D7 | G7: Pending
A8: Oct | E8: =B8-C8-D8 | G8: Pending
A9: Nov | E9: =B9-C9-D9 | G9: Pending
A10: Dec | E10: =B10-C10-D10 | G10: Pending
A11: Jan | E11: =B11-C11-D11 | G11: Pending
A12: Feb | E12: =B12-C12-D12 | G12: Pending
A13: Mar | E13: =B13-C13-D13 | G13: Pending

Sheet All Predictions
A1: All Predictions
M2: =B24
A3: Model Settings | M3: =B25
A4: Scenario | B4: Base | M4: =B26
A5: Weight: Current Trend | B5: 0.6
A6: Weight: Last Year Seasonality | B6: 0.4 | M6: =B28
A7: Best-case uplift | B7: 0.1
A8: Worst-case reduction | B8: 0.1
A10: Month | B10: Actual Sales | C10: Pred Sales | D10: Actual Purchase | E10: Pred Purchase | F10: Actual Expenses | G10: Pred Expenses | H10: Actual Profit | I10: Pred Profit
A11: Apr | B11: ='Current Year Data'!B2 | C11: =IF('Current Year Data'!G2="Actual",B11,($B$5*IFERROR(AVERAGEIF('Current Year Data'!$B$2:$B$13,">0"),0)+$B$6*'Last Year Data'!B2)*IF($B$4="Best",1+$B$7,IF($B$4="Worst",1-$B$8,1))) | D11: ='Current Year Data'!C2 | E11: =IF('Current Year Data'!G2="Actual",D11,($B$5*IFERROR(AVERAGEIF('Current Year Data'!$C$2:$C$13,">0"),0)+$B$6*'Last Year Data'!C2)*IF($B$4="Best",1+$B$7,IF($B$4="Worst",1-$B$8,1))) | F11: ='Current Year Data'!D2 | G11: =IF('Current Year Data'!G2="Actual",F11,($B$5*IFERROR(AVERAGEIF('Current Year Data'!$D$2:$D$13,">0"),0)+$B$6*'Last Year Data'!D2)*IF($B$4="Best",1+$B$7,IF($B$4="Worst",1-$B$8,1))) | H11: ='Current Year Data'!E2 | I11: =C11-E11-G11
A12: May | B12: ='Current Year Data'!B3 | C12: =IF('Current Year Data'!G3="Actual",B12,($B$5*IFERROR(AVERAGEIF('Current Year Data'!$B$2:$B$13,">0"),0)+$B$6*'Last Year Data'!B3)*IF($B$4="Best",1+$B$7,IF($B$4="Worst",1-$B$8,1))) | D12: ='Current Year Data'!C3 | E12: =IF('Current Year Data'!G3="Actual",D12,($B$5*IFERROR(AVERAGEIF('Current Year Data'!$C$2:$C$13,">0"),0)+$B$6*'Last Year Data'!C3)*IF($B$4="Best",1+$B$7,IF($B$4="Worst",1-$B$8,1))) | F12: ='Current Year Data'!D3 | G12: =IF('Current Year Data'!G3="Actual",F12,($B$5*IFERROR(AVERAGEIF('Current Year Data'!$D$2:$D$13,">0"),0)+$B$6*'Last Year Data'!D3)*IF($B$4="Best",1+$B$7,IF($B$4="Worst",1-$B$8,1))) | H12: ='Current Year Data'!E3 | I12: =C12-E12-G12
A13: Jun | B13: ='Current Year Data'!B4 | C13: =IF('Current Year Data'!G4="Actual",B13,($B$5*IFERROR(AVERAGEIF('Current Year Data'!$B$2:$B$13,">0"),0)+$B$6*'Last Year Data'!B4)*IF($B$4="Best",1+$B$7,IF($B$4="Worst",1-$B$8,1))) | D13: ='Current Year Data'!C4 | E13: =IF('Current Year Data'!G4="Actual",D13,($B$5*IFERROR(AVERAGEIF('Current Year Data'!$C$2:$C$13,">0"),0)+$B$6*'Last Year Data'!C4)*IF($B$4="Best",1+$B$7,IF($B$4="Worst",1-$B$8,1))) | F13: ='Current Year Data'!D4 | G13: =IF('Current Year Data'!G4="Actual",F13,($B$5*IFERROR(AVERAGEIF('Current Year Data'!$D$2:$D$13,">0"),0)+$B$6*'Last Year Data'!D4)*IF($B$4="Best",1+$B$7,IF($B$4="Worst",1-$B$8,1))) | H13: ='Current Year Data'!E4 | I13: =C13-E13-G13
A14: Jul | B14: ='Current Year Data'!B5 | C14: =IF('Current Year Data'!G5="Actual",B14,($B$5*IFERROR(AVERAGEIF('Current Year Data'!$B$2:$B$13,">0"),0)+$B$6*'Last Year Data'!B5)*IF($B$4="Best",1+$B$7,IF($B$4="Worst",1-$B$8,1))) | D14: ='Current Year Data'!C5 | E14: =IF('Current Year Data'!G5="Actual",D14,($B$5*IFERROR(AVERAGEIF('Current Year Data'!$C$2:$C$13,">0"),0)+$B$6*'Last Year Data'!C5)*IF($B$4="Best",1+$B$7,IF($B$4="Worst",1-$B$8,1))) | F14: ='Current Year Data'!D5 | G14: =IF('Current Year Data'!G5="Actual",F14,($B$5*IFERROR(AVERAGEIF('Current Year Data'!$D$2:$D$13,">0"),0)+$B$6*'Last Year Data'!D5)*IF($B$4="Best",1+$B$7,IF($B$4="Worst",1-$B$8,1))) | H14: ='Current Year Data'!E5 | I14: =C14-E14-G14
A15: Aug | B15: ='Current Year Data'!B6 | C15: =IF('Current Year Data'!G6="Actual",B15,($B$5*IFERROR(AVERAGEIF('Current Year Data'!$B$2:$B$13,">0"),0)+$B$6*'Last Year Data'!B6)*IF($B$4="Best",1+$B$7,IF($B$4="Worst",1-$B$8,1))) | D15: ='Current Year Data'!C6 | E15: =IF('Current Year Data'!G6="Actual",D15,($B$5*IFERROR(AVERAGEIF('Current Year Data'!$C$2:$C$13,">0"),0)+$B$6*'Last Year Data'!C6)*IF($B$4="Best",1+$B$7,IF($B$4="Worst",1-$B$8,1))) | F15: ='Current Year Data'!D6 | G15: =IF('Current Year Data'!G6="Actual",F15,($B$5*IFERROR(AVERAGEIF('Current Year Data'!$D$2:$D$13,">0"),0)+$B$6*'Last Year Data'!D6)*IF($B$4="Best",1+$B$7,IF($B$4="Worst",1-$B$8,1))) | H15: ='Current Year Data'!E6 | I15: =C15-E15-G15
A16: Sep | B16: ='Current Year Data'!B7 | C16: =IF('Current Year Data'!G7="Actual",B16,($B$5*IFERROR(AVERAGEIF('Current Year Data'!$B$2:$B$13,">0"),0)+$B$6*'Last Year Data'!B7)*IF($B$4="Best",1+$B$7,IF($B$4="Worst",1-$B$8,1))) | D16: ='Current Year Data'!C7 | E16: =IF('Current Year Data'!G7="Actual",D16,($B$5*IFERROR(AVERAGEIF('Current Year Data'!$C$2:$C$13,">0"),0)+$B$6*'Last Year Data'!C7)*IF($B$4="Best",1+$B$7,IF($B$4="Worst",1-$B$8,1))) | F16: ='Current Year Data'!D7 | G16: =IF('Current Year Data'!G7="Actual",F16,($B$5*IFERROR(AVERAGEIF('Current Year Data'!$D$2:$D$13,">0"),0)+$B$6*'Last Year Data'!D7)*IF($B$4="Best",1+$B$7,IF($B$4="Worst",1-$B$8,1))) | H16: ='Current Year Data'!E7 | I16: =C16-E16-G16
A17: Oct | B17: ='Current Year Data'!B8 | C17: =IF('Current Year Data'!G8="Actual",B17,($B$5*IFERROR(AVERAGEIF('Current Year Data'!$B$2:$B$13,">0"),0)+$B$6*'Last Year Data'!B8)*IF($B$4="Best",1+$B$7,IF($B$4="Worst",1-$B$8,1))) | D17: ='Current Year Data'!C8 | E17: =IF('Current Year Data'!G8="Actual",D17,($B$5*IFERROR(AVERAGEIF('Current Year Data'!$C$2:$C$13,">0"),0)+$B$6*'Last Year Data'!C8)*IF($B$4="Best",1+$B$7,IF($B$4="Worst",1-$B$8,1))) | F17: ='Current Year Data'!D8 | G17: =IF('Current Year Data'!G8="Actual",F17,($B$5*IFERROR(AVERAGEIF('Current Year Data'!$D$2:$D$13,">0"),0)+$B$6*'Last Year Data'!D8)*IF($B$4="Best",1+$B$7,IF($B$4="Worst",1-$B$8,1))) | H17: ='Current Year Data'!E8 | I17: =C17-E17-G17
A18: Nov | B18: ='Current Year Data'!B9 | C18: =IF('Current Year Data'!G9="Actual",B18,($B$5*IFERROR(AVERAGEIF('Current Year Data'!$B$2:$B$13,">0"),0)+$B$6*'Last Year Data'!B9)*IF($B$4="Best",1+$B$7,IF($B$4="Worst",1-$B$8,1))) | D18: ='Current Year Data'!C9 | E18: =IF('Current Year Data'!G9="Actual",D18,($B$5*IFERROR(AVERAGEIF('Current Year Data'!$C$2:$C$13,">0"),0)+$B$6*'Last Year Data'!C9)*IF($B$4="Best",1+$B$7,IF($B$4="Worst",1-$B$8,1))) | F18: ='Current Year Data'!D9 | G18: =IF('Current Year Data'!G9="Actual",F18,($B$5*IFERROR(AVERAGEIF('Current Year Data'!$D$2:$D$13,">0"),0)+$B$6*'Last Year Data'!D9)*IF($B$4="Best",1+$B$7,IF($B$4="Worst",1-$B$8,1))) | H18: ='Current Year Data'!E9 | I18: =C18-E18-G18
A19: Dec | B19: ='Current Year Data'!B10 | C19: =IF('Current Year Data'!G10="Actual",B19,($B$5*IFERROR(AVERAGEIF('Current Year Data'!$B$2:$B$13,">0"),0)+$B$6*'Last Year Data'!B10)*IF($B$4="Best",1+$B$7,IF($B$4="Worst",1-$B$8,1))) | D19: ='Current Year Data'!C10 | E19: =IF('Current Year Data'!G10="Actual",D19,($B$5*IFERROR(AVERAGEIF('Current Year Data'!$C$2:$C$13,">0"),0)+$B$6*'Last Year Data'!C10)*IF($B$4="Best",1+$B$7,IF($B$4="Worst",1-$B$8,1))) | F19: ='Current Year Data'!D10 | G19: =IF('Current Year Data'!G10="Actual",F19,($B$5*IFERROR(AVERAGEIF('Current Year Data'!$D$2:$D$13,">0"),0)+$B$6*'Last Year Data'!D10)*IF($B$4="Best",1+$B$7,IF($B$4="Worst",1-$B$8,1))) | H19: ='Current Year Data'!E10 | I19: =C19-E19-G19
A20: Jan | B20: ='Current Year Data'!B11 | C20: =IF('Current Year Data'!G11="Actual",B20,($B$5*IFERROR(AVERAGEIF('Current Year Data'!$B$2:$B$13,">0"),0)+$B$6*'Last Year Data'!B11)*IF($B$4="Best",1+$B$7,IF($B$4="Worst",1-$B$8,1))) | D20: ='Current Year Data'!C11 | E20: =IF('Current Year Data'!G11="Actual",D20,($B$5*IFERROR(AVERAGEIF('Current Year Data'!$C$2:$C$13,">0"),0)+$B$6*'Last Year Data'!C11)*IF($B$4="Best",1+$B$7,IF($B$4="Worst",1-$B$8,1))) | F20: ='Current Year Data'!D11 | G20: =IF('Current Year Data'!G11="Actual",F20,($B$5*IFERROR(AVERAGEIF('Current Year Data'!$D$2:$D$13,">0"),0)+$B$6*'Last Year Data'!D11)*IF($B$4="Best",1+$B$7,IF($B$4="Worst",1-$B$8,1))) | H20: ='Current Year Data'!E11 | I20: =C20-E20-G20
A21: Feb | B21: ='Current Year Data'!B12 | C21: =IF('Current Year Data'!G12="Actual",B21,($B$5*IFERROR(AVERAGEIF('Current Year Data'!$B$2:$B$13,">0"),0)+$B$6*'Last Year Data'!B12)*IF($B$4="Best",1+$B$7,IF($B$4="Worst",1-$B$8,1))) | D21: ='Current Year Data'!C12 | E21: =IF('Current Year Data'!G12="Actual",D21,($B$5*IFERROR(AVERAGEIF('Current Year Data'!$C$2:$C$13,">0"),0)+$B$6*'Last Year Data'!C12)*IF($B$4="Best",1+$B$7,IF($B$4="Worst",1-$B$8,1))) | F21: ='Current Year Data'!D12 | G21: =IF('Current Year Data'!G12="Actual",F21,($B$5*IFERROR(AVERAGEIF('Current Year Data'!$D$2:$D$13,">0"),0)+$B$6*'Last Year Data'!D12)*IF($B$4="Best",1+$B$7,IF($B$4="Worst",1-$B$8,1))) | H21: ='Current Year Data'!E12 | I21: =C21-E21-G21
A22: Mar | B22: ='Current Year Data'!B13 | C22: =IF('Current Year Data'!G13="Actual",B22,($B$5*IFERROR(AVERAGEIF('Current Year Data'!$B$2:$B$13,">0"),0)+$B$6*'Last Year Data'!B13)*IF($B$4="Best",1+$B$7,IF($B$4="Worst",1-$B$8,1))) | D22: ='Current Year Data'!C13 | E22: =IF('Current Year Data'!G13="Actual",D22,($B$5*IFERROR(AVERAGEIF('Current Year Data'!$C$2:$C$13,">0"),0)+$B$6*'Last Year Data'!C13)*IF($B$4="Best",1+$B$7,IF($B$4="Worst",1-$B$8,1))) | F22: ='Current Year Data'!D13 | G22: =IF('Current Year Data'!G13="Actual",F22,($B$5*IFERROR(AVERAGEIF('Current Year Data'!$D$2:$D$13,">0"),0)+$B$6*'Last Year Data'!D13)*IF($B$4="Best",1+$B$7,IF($B$4="Worst",1-$B$8,1))) | H22: ='Current Year Data'!E13 | I22: =C22-E22-G22
A24: Predicted Full-Year Sales | B24: =SUM(C11:C22)
A25: Predicted Full-Year Purchase | B25: =SUM(E11:E22)
A26: Predicted Full-Year Profit | B26: =SUM(I11:I22)
A27: Estimated Taxable Income | B27: =MAX(B26-'Main (All in One)'!B12,0)
A28: Current FY Predicted Tax Payable | B28: =B27*'Main (All in One)'!B9*(1+'Main (All in One)'!B10+'Main (All in One)'!B11)
A29: Tax Already Paid | B29: ='Main (All in One)'!B13
A30: Net Payable | B30: =MAX(B28-B29,0)
A31: Expected Owner Monthly Payment | B31: =IF(COUNTIF('Current Year Data'!G2:G13,"Pending")>0,B30/COUNTIF('Current Year Data'!G2:G13,"Pending"),0)
A32: Q1 Tax Estimate | B32: =SUM(I11:I13)*'Main (All in One)'!B9*(1+'Main (All in One)'!B10+'Main (All in One)'!B11)
A33: Q2 Tax Estimate | B33: =SUM(I14:I16)*'Main (All in One)'!B9*(1+'Main (All in One)'!B10+'Main (All in One)'!B11)
A34: Q3 Tax Estimate | B34: =SUM(I17:I19)*'Main (All in One)'!B9*(1+'Main (All in One)'!B10+'Main (All in One)'!B11)
A35: Q4 Tax Estimate | B35: =SUM(I20:I22)*'Main (All in One)'!B9*(1+'Main (All in One)'!B10+'Main (All in One)'!B11)
